restmachine_web/__init__.py
restmachine_web/_version.py
restmachine_web/static_router.py
restmachine_web-0.1.1.dist-info/METADATA
restmachine_web-0.1.1.dist-info/WHEEL
restmachine_web-0.1.1.dist-info/top_level.txt
restmachine_web-0.1.1.dist-info/RECORD
